pyalb/__init__.py
pyalb/cli.py
pyalb/health_checker.py
pyalb/load_balancer.py
pyalb/main.py
pyalb/server.py
pyalb/routing/__init__.py
pyalb/routing/base.py
pyalb/routing/context.py
pyalb/routing/strategies/__init__.py
pyalb/routing/strategies/random_selection.py
pyalb/routing/strategies/round_robbin.py
pyalb-1.1.2.dist-info/LICENSE
pyalb-1.1.2.dist-info/METADATA
pyalb-1.1.2.dist-info/WHEEL
pyalb-1.1.2.dist-info/entry_points.txt
pyalb-1.1.2.dist-info/top_level.txt
pyalb-1.1.2.dist-info/RECORD
