Metadata-Version: 2.1
Name: pyalb
Version: 1.1.2
Summary: A simple application load balancer
Author-email: Aryan Sharma <aryansharma.work101@gmail.com>
License: MIT License
Project-URL: Homepage, https://github.com/AryanSharma5/pyalb
Project-URL: Issues, https://github.com/AryanSharma5/pyalb/issues
Keywords: python,load balancer,flask,round robbin,random selection,strategy,pyalb,load balancer cli,circleci
Classifier: Development Status :: 2 - Pre-Alpha
Classifier: License :: OSI Approved :: MIT License
Classifier: Framework :: Flask
Classifier: Programming Language :: Python
Classifier: Programming Language :: Python :: 3.10
Classifier: Intended Audience :: Developers
Classifier: Topic :: Software Development
Classifier: Topic :: Software Development :: Libraries
Classifier: Topic :: Software Development :: Libraries :: Python Modules
Requires-Python: >=3.8
License-File: LICENSE
Requires-Dist: importlib-metadata
Requires-Dist: Flask ==3.0.0
Requires-Dist: requests ==2.31.0
